ggoat/__init__.py
ggoat/aes.py
ggoat/bistro.py
ggoat/bridge.py
ggoat/core.py
ggoat/geoms.py
ggoat/geospatial.py
ggoat/labels.py
ggoat/positions.py
ggoat/scales.py
ggoat/themes.py
ggoat/utils.py
ggoat/assets/lets-plot.min.js
ggoat-0.2.0.dist-info/licenses/LICENSE
ggoat-0.2.0.dist-info/METADATA
ggoat-0.2.0.dist-info/WHEEL
ggoat-0.2.0.dist-info/top_level.txt
ggoat-0.2.0.dist-info/RECORD
