Metadata-Version: 2.4
Name: ggoat
Version: 0.2.0
Summary: Grammar of Graphics for Python - optimized for Pyodide and browser environments
Author-email: ggoat development team <contact@ggoat.dev>
License: MIT
Project-URL: Bug Tracker, https://github.com/ggoat/ggoat/issues
Project-URL: Documentation, https://ggoat.readthedocs.io/
Project-URL: Source, https://github.com/ggoat/ggoat
Keywords: visualization,plotting,grammar-of-graphics,ggplot,pyodide,jupyter
Classifier: Development Status :: 4 - Beta
Classifier: Intended Audience :: Developers
Classifier: Intended Audience :: Science/Research
Classifier: License :: OSI Approved :: MIT License
Classifier: Operating System :: OS Independent
Classifier: Programming Language :: Python :: 3
Classifier: Programming Language :: Python :: 3.8
Classifier: Programming Language :: Python :: 3.9
Classifier: Programming Language :: Python :: 3.10
Classifier: Programming Language :: Python :: 3.11
Classifier: Programming Language :: Python :: 3.12
Classifier: Topic :: Scientific/Engineering :: Visualization
Classifier: Topic :: Software Development :: Libraries :: Python Modules
Classifier: Framework :: Jupyter
Requires-Python: >=3.8
License-File: LICENSE
Provides-Extra: pandas
Requires-Dist: pandas>=1.0.0; extra == "pandas"
Provides-Extra: numpy
Requires-Dist: numpy>=1.18.0; extra == "numpy"
Provides-Extra: jupyter
Requires-Dist: ipython>=7.0.0; extra == "jupyter"
Requires-Dist: jupyter>=1.0.0; extra == "jupyter"
Provides-Extra: letsplot
Requires-Dist: lets-plot>=3.0.0; extra == "letsplot"
Provides-Extra: dev
Requires-Dist: pytest>=6.0.0; extra == "dev"
Requires-Dist: pytest-cov>=2.0.0; extra == "dev"
Requires-Dist: black>=22.0.0; extra == "dev"
Requires-Dist: isort>=5.10.0; extra == "dev"
Requires-Dist: flake8>=4.0.0; extra == "dev"
Requires-Dist: mypy>=0.900; extra == "dev"
Requires-Dist: pandas>=1.0.0; extra == "dev"
Requires-Dist: numpy>=1.18.0; extra == "dev"
Provides-Extra: docs
Requires-Dist: sphinx>=4.0.0; extra == "docs"
Requires-Dist: sphinx-rtd-theme>=1.0.0; extra == "docs"
Requires-Dist: myst-parser>=0.18.0; extra == "docs"
Requires-Dist: sphinx-autobuild>=2021.3.14; extra == "docs"
Requires-Dist: sphinx-copybutton>=0.5.0; extra == "docs"
Provides-Extra: all
Requires-Dist: pandas>=1.0.0; extra == "all"
Requires-Dist: numpy>=1.18.0; extra == "all"
Requires-Dist: ipython>=7.0.0; extra == "all"
Requires-Dist: lets-plot>=3.0.0; extra == "all"
Dynamic: license-file
